llm_grader/__init__.py
llm_grader/code_evaluator.py
llm_grader/scoring_impl.py
rubric_grader-0.1.0.dist-info/METADATA
rubric_grader-0.1.0.dist-info/WHEEL
rubric_grader-0.1.0.dist-info/top_level.txt
rubric_grader-0.1.0.dist-info/RECORD
