Metadata-Version: 2.4
Name: rubric-grader
Version: 0.1.0
Summary: A Python library for rubric-guided grading with LLMs
Author-email: Arnav Ramamoorthy <arnav.ramamorthy@gmail.com>
License: MIT
Project-URL: Homepage, https://github.com/BITS-Pilani-GRC/Rubric-Grader
Project-URL: Issues, https://github.com/BITS-Pilani-GRC/Rubric-Grader/issues
Requires-Python: >=3.9
Requires-Dist: transformers
Requires-Dist: torch
Requires-Dist: pandas
